LICENSE
README.md
setup.py
Piltdown.egg-info/PKG-INFO
Piltdown.egg-info/SOURCES.txt
Piltdown.egg-info/dependency_links.txt
Piltdown.egg-info/top_level.txt
piltdown/__init__.py
piltdown/bar_chart.py
piltdown/column_sparkline.py
piltdown/dot_chart.py
piltdown/hbar_chart.py
piltdown/hdot_chart.py
piltdown/literals.py
piltdown/scaled_up_number.py
piltdown/table.py
piltdown/tally.py
piltdown/util.py
piltdown/waffle.py
piltdown/win_loss_sparkline.py