Metadata-Version: 2.1
Name: Piltdown
Version: 0.1.1
Summary: Unicode data viz for your Twitter posts.
Home-page: http://github.com/evanswinner/piltdown
Author: Evans Winner
Author-email: evans.winner@gmail.com
License: LICENSE
Platform: UNKNOWN
License-File: LICENSE
